Workbook
Name aporte: Projeto!$E$15
Name patrimonio: Projeto!$E$18
Name qtd_anos: Projeto!$E$16
Name rendimento_carteira: Projeto!$E$11
Name salario: Projeto!$E$10
Name sugestao_ivenstimento: Projeto!$E$12
Name taxa_mensal: Projeto!$E$17

Sheet Projeto
C9: CONFIGURAÇÕES
C10: Salário | E10: 4200
C11: Rendimento Carteira | E11: 0.006
C12: Sugestão de Investimento (30%) | E12: =E10*30% -> 1260
C14: Investimento Mensal
C15: Quanto investir por mês? | E15: 200
C16: Por quantos anos? | E16: 5
C17: Taxa de Rendimento mensal? | E17: 0.01079
C18: Patrimônio acumulado: | E18: =FV(taxa_mensal,qtd_anos*12,aporte*-1) -> 16755.383
C19: Dividendos Mensais: | E19: =patrimonio*rendimento_carteira -> 100.5323
C21: Cenários | E21: Dividendo
A22: 2 | C22: Quanto em 2 Anos? | D22: =FV($E$17,$A22*12,$E$15*-1) -> 5445.5255 | E22: =D22*$E$11+rendimento_carteira -> 32.679153
A23: 5 | C23: Quanto em 5 Anos? | D23: =FV($E$17,$A23*12,$E$15*-1) -> 16755.383 | E23: =D23*$E$11+rendimento_carteira -> 100.5383
A24: 10 | C24: Quanto em 10 Anos? | D24: =FV($E$17,$A24*12,$E$15*-1) -> 48656.843 | E24: =D24*$E$11+rendimento_carteira -> 291.94706
A25: 20 | C25: Quanto em 20 Anos? | D25: =FV($E$17,$A25*12,$E$15*-1) -> 225039.68 | E25: =D25*$E$11+rendimento_carteira -> 1350.2441
A26: 30 | C26: Quanto em 30 Anos? | D26: =FV($E$17,$A26*12,$E$15*-1) -> 864433.93 | E26: =D26*$E$11+rendimento_carteira -> 5186.6096
C29: PERFIL | D29: Agressivo
C30: INVESTIMENTO MENSAL | D30: =aporte -> 200
C32: TIPO DE FII | D32: PERCENTUAL SUGERIDO | E32: VALORES
C33: PAPEL | D33: =VLOOKUP($D$29&"-"&C33,TB_APOIO!$A:$D,4,FALSE) -> 0.5 | E33: =D33*$D$30 -> 100
C34: TIJOLO | D34: =VLOOKUP($D$29&"-"&C34,TB_APOIO!$A:$D,4,FALSE) -> 0.1 | E34: =D34*$D$30 -> 20
C35: HÍBRIDOS | D35: =VLOOKUP($D$29&"-"&C35,TB_APOIO!$A:$D,4,FALSE) -> 0.05 | E35: =D35*$D$30 -> 10
C36: FOFs | D36: =VLOOKUP($D$29&"-"&C36,TB_APOIO!$A:$D,4,FALSE) -> 0.05 | E36: =D36*$D$30 -> 10
C37: DESENVOLVIMENTO | D37: =VLOOKUP($D$29&"-"&C37,TB_APOIO!$A:$D,4,FALSE) -> 0.2 | E37: =D37*$D$30 -> 40
C38: HOTELARIAS | D38: =VLOOKUP($D$29&"-"&C38,TB_APOIO!$A:$D,4,FALSE) -> 0.1 | E38: =D38*$D$30 -> 20
E39: =SUM(E33:E38) -> 200

Sheet TB_APOIO
A2: CHAVE | B2: PERFIL | C2: TIPOS DE FII | D2: %
A3: =B3&"-"&C3 -> Conservador-PAPEL | B3: Conservador | C3: PAPEL | D3: 0.3 | H3: %
A4: =B4&"-"&C4 -> Conservador-TIJOLO | B4: Conservador | C4: TIJOLO | D4: 0.5 | G4: Moderado-TIJOLO | H4: =VLOOKUP(G4,$A:$D,4,) -> 0.35
A5: =B5&"-"&C5 -> Conservador-HÍBRIDOS | B5: Conservador | C5: HÍBRIDOS | D5: 0.1
A6: =B6&"-"&C6 -> Conservador-FOFs | B6: Conservador | C6: FOFs | D6: 0.1
A7: =B7&"-"&C7 -> Conservador-DESENVOLVIMENTO | B7: Conservador | C7: DESENVOLVIMENTO | D7: 0
A8: =B8&"-"&C8 -> Conservador-HOTELARIAS | B8: Conservador | C8: HOTELARIAS | D8: 0
A9: =B9&"-"&C9 -> Moderado-PAPEL | B9: Moderado | C9: PAPEL | D9: 0.32
A10: =B10&"-"&C10 -> Moderado-TIJOLO | B10: Moderado | C10: TIJOLO | D10: 0.35
A11: =B11&"-"&C11 -> Moderado-HÍBRIDOS | B11: Moderado | C11: HÍBRIDOS | D11: 0.08
A12: =B12&"-"&C12 -> Moderado-FOFs | B12: Moderado | C12: FOFs | D12: 0.05
A13: =B13&"-"&C13 -> Moderado-DESENVOLVIMENTO | B13: Moderado | C13: DESENVOLVIMENTO | D13: 0.1
A14: =B14&"-"&C14 -> Moderado-HOTELARIAS | B14: Moderado | C14: HOTELARIAS | D14: 0.1
A15: =B15&"-"&C15 -> Agressivo-PAPEL | B15: Agressivo | C15: PAPEL | D15: 0.5
A16: =B16&"-"&C16 -> Agressivo-TIJOLO | B16: Agressivo | C16: TIJOLO | D16: 0.1
... A20: =B20&"-"&C20 -> Agressivo-HOTELARIAS | B20: Agressivo | C20: HOTELARIAS | D20: 0.1
